{"repo": {"timestamp": 1722409591000}, "packages": {"li.songe.gkd": {"versions": {"59039f5d44aaa176dd54768f2087b64a29fac7dac3e7c3c0e15f7b57d1b4d9e6": {"added": 1722405984000, "file": {"name": "/gkd-v1.6.4.apk", "sha256": "59039f5d44aaa176dd54768f2087b64a29fac7dac3e7c3c0e15f7b57d1b4d9e6", "size": 5861139}, "manifest": {"nativecode": ["arm64-v8a", "x86_64"], "versionName": "1.6.4", "versionCode": 19, "usesSdk": {"minSdkVersion": 26, "targetSdkVersion": 34}, "signer": {"sha256": ["27a532fff3cf13524a89a86adf99ac05ce708dd781680b04846d4b9fb795a391"]}, "usesPermission": [{"name": "android.permission.FOREGROUND_SERVICE"}, {"name": "android.permission.FOREGROUND_SERVICE_MEDIA_PLAYBACK"}, {"name": "android.permission.FOREGROUND_SERVICE_DATA_SYNC"}, {"name": "android.permission.FOREGROUND_SERVICE_MEDIA_PROJECTION"}, {"name": "android.permission.INTERNET"}, {"name": "android.permission.ACCESS_NETWORK_STATE"}, {"name": "android.permission.QUERY_ALL_PACKAGES"}, {"name": "android.permission.POST_NOTIFICATIONS"}, {"name": "android.permission.SYSTEM_ALERT_WINDOW"}, {"name": "android.permission.REQUEST_INSTALL_PACKAGES"}, {"name": "android.permission.WRITE_EXTERNAL_STORAGE", "maxSdkVersion": 28}, {"name": "li.songe.gkd.DYNAMIC_RECEIVER_NOT_EXPORTED_PERMISSION"}, {"name": "moe.shizuku.manager.permission.API_V23"}, {"name": "android.permission.READ_EXTERNAL_STORAGE", "maxSdkVersion": 28}]}}, "39b697027eaa31294c1f7c5229d827c3f5cf0aefb0cdbd711ae09f16c14a984b": {"added": 1722405984000, "file": {"name": "/gkd-v1.6.3.apk", "sha256": "39b697027eaa31294c1f7c5229d827c3f5cf0aefb0cdbd711ae09f16c14a984b", "size": 5861139}, "manifest": {"nativecode": ["arm64-v8a", "x86_64"], "versionName": "1.6.3", "versionCode": 18, "usesSdk": {"minSdkVersion": 26, "targetSdkVersion": 34}, "signer": {"sha256": ["27a532fff3cf13524a89a86adf99ac05ce708dd781680b04846d4b9fb795a391"]}, "usesPermission": [{"name": "android.permission.FOREGROUND_SERVICE"}, {"name": "android.permission.FOREGROUND_SERVICE_MEDIA_PLAYBACK"}, {"name": "android.permission.FOREGROUND_SERVICE_DATA_SYNC"}, {"name": "android.permission.FOREGROUND_SERVICE_MEDIA_PROJECTION"}, {"name": "android.permission.INTERNET"}, {"name": "android.permission.ACCESS_NETWORK_STATE"}, {"name": "android.permission.QUERY_ALL_PACKAGES"}, {"name": "android.permission.POST_NOTIFICATIONS"}, {"name": "android.permission.SYSTEM_ALERT_WINDOW"}, {"name": "android.permission.REQUEST_INSTALL_PACKAGES"}, {"name": "android.permission.WRITE_EXTERNAL_STORAGE", "maxSdkVersion": 28}, {"name": "li.songe.gkd.DYNAMIC_RECEIVER_NOT_EXPORTED_PERMISSION"}, {"name": "moe.shizuku.manager.permission.API_V23"}, {"name": "android.permission.READ_EXTERNAL_STORAGE", "maxSdkVersion": 28}]}}}}, "moe.tarsin.ehviewer": {"metadata": {"lastUpdated": 1722409003000}, "versions": {"cc8b9895a754693d78059c2a9228d12ba4ddfdd5d6e8cb1b8e64afcc00f8db3f": {"added": 1722409003000, "file": {"name": "/EhViewer-UjuiUjuMandan-1.11.7-cc-default-universal.apk", "sha256": "cc8b9895a754693d78059c2a9228d12ba4ddfdd5d6e8cb1b8e64afcc00f8db3f", "size": 25393376}, "manifest": {"nativecode": ["arm64-v8a", "armeabi-v7a", "x86_64"], "versionName": "1.11.7-cc", "versionCode": 180058, "usesSdk": {"minSdkVersion": 26, "targetSdkVersion": 35}, "signer": {"sha256": ["5d91dff13b6489a9cfadbb197b3e795eefc8c39f849c4543f32c160720fb40a6"]}, "usesPermission": [{"name": "android.permission.POST_NOTIFICATIONS"}, {"name": "android.permission.INTERNET"}, {"name": "android.permission.ACCESS_NETWORK_STATE"}, {"name": "android.permission.FOREGROUND_SERVICE_DATA_SYNC"}, {"name": "android.permission.REQUEST_INSTALL_PACKAGES"}, {"name": "android.permission.WRITE_EXTERNAL_STORAGE", "maxSdkVersion": 28}, {"name": "android.permission.USE_BIOMETRIC"}, {"name": "android.permission.USE_FINGERPRINT"}, {"name": "android.permission.WAKE_LOCK"}, {"name": "android.permission.RECEIVE_BOOT_COMPLETED"}, {"name": "android.permission.FOREGROUND_SERVICE"}, {"name": "moe.tarsin.ehviewer.DYNAMIC_RECEIVER_NOT_EXPORTED_PERMISSION"}, {"name": "android.permission.READ_EXTERNAL_STORAGE", "maxSdkVersion": 28}]}, "antiFeatures": {"NonFreeNet": {}, "NSFW": {}, "NoSourceSince": {}}}}}, "moe.tarsin.ehviewer.m": {"metadata": {"lastUpdated": 1722409004000, "name": {"en-US": "EhViewer-FooIbar-Marshmallow"}}, "versions": {"03e17060c2ce72aac2f24e27de846c6978a5de14502b850ba5e326600b693d39": {"antiFeatures": {"NoSourceSince": null}}, "be2c1f7298a05c1b8fbc5385b95fbf008a710f533198436ec6019391e84fba3b": {"added": 1722409004000, "file": {"name": "/EhViewer-UjuiUjuMandan-1.11.7-cc-marshmallow-universal.apk", "sha256": "be2c1f7298a05c1b8fbc5385b95fbf008a710f533198436ec6019391e84fba3b", "size": 26339860}, "manifest": {"nativecode": ["arm64-v8a", "armeabi-v7a", "x86_64"], "versionName": "1.11.7-cc-M", "versionCode": 180058, "usesSdk": {"minSdkVersion": 23, "targetSdkVersion": 35}, "signer": {"sha256": ["5d91dff13b6489a9cfadbb197b3e795eefc8c39f849c4543f32c160720fb40a6"]}, "usesPermission": [{"name": "android.permission.POST_NOTIFICATIONS"}, {"name": "android.permission.INTERNET"}, {"name": "android.permission.ACCESS_NETWORK_STATE"}, {"name": "android.permission.FOREGROUND_SERVICE_DATA_SYNC"}, {"name": "android.permission.REQUEST_INSTALL_PACKAGES"}, {"name": "android.permission.WRITE_EXTERNAL_STORAGE", "maxSdkVersion": 28}, {"name": "android.permission.USE_BIOMETRIC"}, {"name": "android.permission.USE_FINGERPRINT"}, {"name": "android.permission.WAKE_LOCK"}, {"name": "android.permission.RECEIVE_BOOT_COMPLETED"}, {"name": "android.permission.FOREGROUND_SERVICE"}, {"name": "moe.tarsin.ehviewer.m.DYNAMIC_RECEIVER_NOT_EXPORTED_PERMISSION"}, {"name": "android.permission.READ_EXTERNAL_STORAGE", "maxSdkVersion": 28}]}, "antiFeatures": {"NonFreeNet": {}, "NSFW": {}}}}}}}